topologicpy/Aperture.py
topologicpy/Cell.py
topologicpy/CellComplex.py
topologicpy/Cluster.py
topologicpy/Color.py
topologicpy/Context.py
topologicpy/DGL.py
topologicpy/Dictionary.py
topologicpy/Edge.py
topologicpy/EnergyModel.py
topologicpy/Face.py
topologicpy/Graph.py
topologicpy/Grid.py
topologicpy/Helper.py
topologicpy/Honeybee.py
topologicpy/Matrix.py
topologicpy/Neo4j.py
topologicpy/Plotly.py
topologicpy/Polyskel.py
topologicpy/Shell.py
topologicpy/Speckle.py
topologicpy/Topology.py
topologicpy/Vector.py
topologicpy/Vertex.py
topologicpy/Wire.py
topologicpy/__init__.py
topologicpy/version.py
topologicpy-6.0.0.dist-info/LICENSE
topologicpy-6.0.0.dist-info/METADATA
topologicpy-6.0.0.dist-info/WHEEL
topologicpy-6.0.0.dist-info/top_level.txt
topologicpy-6.0.0.dist-info/RECORD
