Metadata-Version: 2.1
Name: topologicpy
Version: 6.0.0
Summary: An Advanced Spatial Modelling and Analysis Software Library for Architecture, Engineering, and Construction.
Author-email: Wassim Jabi <wassim.jabi@gmail.com>
License: GNU AFFERO GENERAL PUBLIC LICENSE
Project-URL: Homepage, https://github.com/wassimj/TopologicPy
Project-URL: Bug Tracker, https://github.com/wassimj/TopologicPy/issues
Project-URL: Documentation, https://topologic.app/topologicpy_doc/
Classifier: Programming Language :: Python :: 3
Classifier: License :: OSI Approved :: GNU General Public License v3 (GPLv3)
Classifier: Operating System :: OS Independent
Requires-Python: <3.13,>=3.8
License-File: LICENSE
Requires-Dist: numpy >=1.18.0
Requires-Dist: scipy >=1.4.1
Requires-Dist: pandas
Requires-Dist: tqdm
Requires-Dist: plotly
Requires-Dist: lark
Requires-Dist: topologic-core >=7.0.1
Provides-Extra: test
Requires-Dist: pytest-xdist >=2.4.0 ; extra == 'test'
